CHANGELOG.md
MANIFEST.in
README.rst
setup.cfg
setup.py
tailbone_quickbooks/__init__.py
tailbone_quickbooks/_version.py
tailbone_quickbooks.egg-info/PKG-INFO
tailbone_quickbooks.egg-info/SOURCES.txt
tailbone_quickbooks.egg-info/dependency_links.txt
tailbone_quickbooks.egg-info/requires.txt
tailbone_quickbooks.egg-info/top_level.txt
tailbone_quickbooks/templates/quickbooks/exportable-invoices/index.mako
tailbone_quickbooks/templates/quickbooks/exportable-invoices/view.mako
tailbone_quickbooks/templates/quickbooks/exports/invoice/view.mako
tailbone_quickbooks/templates/vendors/quickbooks_bank_accounts_js.mako
tailbone_quickbooks/templates/vendors/quickbooks_bank_accounts_widget.mako
tailbone_quickbooks/views/__init__.py
tailbone_quickbooks/views/departments.py
tailbone_quickbooks/views/stores.py
tailbone_quickbooks/views/vendors.py
tailbone_quickbooks/views/quickbooks/__init__.py
tailbone_quickbooks/views/quickbooks/invoices.py