Metadata-Version: 2.1
Name: tailbone-quickbooks
Version: 0.1.7
Summary: Tailbone integration package for Quickbooks
Home-page: https://rattailproject.org/
Author: Lance Edgar
Author-email: lance@edbob.org
Classifier: Development Status :: 3 - Alpha
Classifier: Environment :: Web Environment
Classifier: Intended Audience :: Developers
Classifier: License :: OSI Approved :: GNU General Public License v3 or later (GPLv3+)
Classifier: Natural Language :: English
Classifier: Operating System :: OS Independent
Classifier: Programming Language :: Python
Classifier: Programming Language :: Python :: 3
Classifier: Topic :: Office/Business
Classifier: Topic :: Software Development :: Libraries :: Python Modules
Requires-Dist: rattail-quickbooks
Requires-Dist: Tailbone
